[
  {
    "Id": 42,
    "Nome": "Botafogo",
    "Descricao": "Fogão",
    "Votos": 0,
    "ImageUrl": "https://upload.wikimedia.org/wikipedia/commons/thumb/5/52/Botafogo_de_Futebol_e_Regatas_logo.svg/800px-Botafogo_de_Futebol_e_Regatas_logo.svg.png",
    "MensagemVencendo": "Passei na Frente!",
    "MensagemPerdendo": "Não quero perder de novo não...",
    "MensagemEmpatado": "Empatou... Votem em mim!",
    "MensagemNoCentro": "Me esqueceream no meio da tabela..."
  },
  {
    "Id": 39,
    "Nome": "Flamengo",
    "Descricao": "Mengão",
    "Votos": 0,
    "ImageUrl": "https://upload.wikimedia.org/wikipedia/commons/thumb/2/2e/Flamengo_braz_logo.svg/800px-Flamengo_braz_logo.svg.png",
    "MensagemVencendo": "Tô Ganhando, Mengoooo!",
    "MensagemPerdendo": "Virei Lanterninha do Campeonato",
    "MensagemEmpatado": "Empatou... Votem em mim!",
    "MensagemNoCentro": "Vamos pra cima deles Mengo"
  },
  {
    "Id": 40,
    "Nome": "Fluminense",
    "Descricao": "Flusão",
    "Votos": 0,
    "ImageUrl": "https://upload.wikimedia.org/wikipedia/pt/thumb/a/a3/FFC_escudo.svg/1200px-FFC_escudo.svg.png",
    "MensagemVencendo": "Passei na Frente, Flusão!",
    "MensagemPerdendo": "Não quero perder de novo não...",
    "MensagemEmpatado": "Empatou... Votem em mim!",
    "MensagemNoCentro": "Virei um centrão..."
  },
  {
    "Id": 41,
    "Nome": "Vasco",
    "Descricao": "Vascão",
    "Votos": 0,
    "ImageUrl": "https://upload.wikimedia.org/wikipedia/pt/a/ac/CRVascodaGama.png",
    "MensagemVencendo": "Passei na Frente!",
    "MensagemPerdendo": "Não quero perder de novo não...",
    "MensagemEmpatado": "Empatou... Votem em mim!",
    "MensagemNoCentro": "Me esqueceream no meio da tabela..."
  }
]
